exceljsontoolkit/__init__.py
exceljsontoolkit/context_map.py
exceljsontoolkit/converter.py
exceljsontoolkit/loader.py
exceljsontoolkit-0.2.1.dist-info/licenses/LICENCE
exceljsontoolkit-0.2.1.dist-info/METADATA
exceljsontoolkit-0.2.1.dist-info/WHEEL
exceljsontoolkit-0.2.1.dist-info/top_level.txt
exceljsontoolkit-0.2.1.dist-info/RECORD
