Metadata-Version: 2.4
Name: exceljsontoolkit
Version: 0.2.1
Summary: A toolkit to extract structured JSON from Excel, load it, and generate context maps.
Home-page: https://github.com/yourusername/exceljsontoolkit
Author: Mahdi Jaffery
Classifier: Programming Language :: Python :: 3
Classifier: License :: OSI Approved :: MIT License
Requires-Python: >=3.7
License-File: LICENCE
Requires-Dist: pandas
Requires-Dist: openai
Requires-Dist: python-dotenv
Dynamic: author
Dynamic: classifier
Dynamic: description
Dynamic: description-content-type
Dynamic: home-page
Dynamic: license-file
Dynamic: requires-dist
Dynamic: requires-python
Dynamic: summary
